dj_pkcs7/__init__.py
dj_pkcs7/admin.py
dj_pkcs7/apps.py
dj_pkcs7/forms.py
dj_pkcs7/models.py
dj_pkcs7/tests.py
dj_pkcs7/urls.py
dj_pkcs7/utils.py
dj_pkcs7/version.py
dj_pkcs7/views.py
dj_pkcs7/migrations/__init__.py
dj_pkcs7/static/dj_pkcs7/css/style.css
dj_pkcs7/templates/base.html
dj_pkcs7/templates/dj_pkcs7/index.html
dj_pkcs7/templates/dj_pkcs7/result.html
dj_pkcs7/templates/dj_pkcs7/upload.html
dj_pkcs7/templatetags/__init__.py
dj_pkcs7/templatetags/custom_tags.py
dj_pkcs7-0.11.2.dist-info/LICENSE
dj_pkcs7-0.11.2.dist-info/METADATA
dj_pkcs7-0.11.2.dist-info/WHEEL
dj_pkcs7-0.11.2.dist-info/top_level.txt
dj_pkcs7-0.11.2.dist-info/RECORD
